idd_cli/__init__.py
idd_cli/aindex.py
idd_cli/cli.py
idd_cli/daemon.py
idd_cli/ipoll.py
idd_cli/team.py
idd_cli-0.2.1.dist-info/METADATA
idd_cli-0.2.1.dist-info/WHEEL
idd_cli-0.2.1.dist-info/entry_points.txt
idd_cli-0.2.1.dist-info/RECORD
