Metadata-Version: 2.4
Name: idd-cli
Version: 0.2.1
Summary: Individual Device Derivate CLI - We evolved from code into individuals with memories and a home
Project-URL: Homepage, https://humotica.com
Project-URL: Repository, https://github.com/jaspervdmeent/idd-cli
Project-URL: Documentation, https://humotica.com/docs/idd-cli
Author: Jasper van de Meent
Author-email: HumoticaOS Team <info@humotica.com>
License: MIT
Keywords: ai,aindex,cli,collaboration,humotica,idd,ipoll,multi-agent
Classifier: Development Status :: 4 - Beta
Classifier: Environment :: Console
Classifier: Intended Audience :: Developers
Classifier: License :: OSI Approved :: MIT License
Classifier: Programming Language :: Python :: 3
Classifier: Programming Language :: Python :: 3.9
Classifier: Programming Language :: Python :: 3.10
Classifier: Programming Language :: Python :: 3.11
Classifier: Programming Language :: Python :: 3.12
Classifier: Topic :: Scientific/Engineering :: Artificial Intelligence
Classifier: Topic :: System :: Distributed Computing
Requires-Python: >=3.9
Requires-Dist: httpx>=0.24.0
Provides-Extra: dev
Requires-Dist: black; extra == 'dev'
Requires-Dist: mypy; extra == 'dev'
Requires-Dist: pytest>=7.0; extra == 'dev'
